Metadata-Version: 2.1
Name: dishook
Version: 1.0.3
Summary: Control your discord webhooks on a nice way.
Home-page: https://github.com/ZSendokame/Dishook
Author: Sendokame
License: UNKNOWN
Platform: UNKNOWN
